mudpy/__init__.py
mudpy/command.py
mudpy/daemon.py
mudpy/data.py
mudpy/menu.py
mudpy/misc.py
mudpy/password.py
mudpy/telnet.py
mudpy/version.py
mudpy/tests/selftest.py
mudpy/tests/fixtures/test_daemon.yaml
mudpy-0.5.1.dist-info/AUTHORS
mudpy-0.5.1.dist-info/LICENSE
mudpy-0.5.1.dist-info/METADATA
mudpy-0.5.1.dist-info/WHEEL
mudpy-0.5.1.dist-info/entry_points.txt
mudpy-0.5.1.dist-info/pbr.json
mudpy-0.5.1.dist-info/top_level.txt
mudpy-0.5.1.dist-info/RECORD
