Metadata-Version: 2.1
Name: mudpy
Version: 0.5.1
Summary: The mudpy MUD server engine.
Author: Jeremy Stanley
Author-email: fungi@yuggoth.org
Maintainer: Jeremy Stanley
Maintainer-email: fungi@yuggoth.org
Project-URL: Big ChangeLog, https://mudpy.org/clog/mudpy/
Project-URL: Browse Source, https://mudpy.org/code/mudpy/
Project-URL: Bug Reporting, https://mudpy.org/bugs/mudpy/
Project-URL: Documentation, https://mudpy.org/docs/mudpy/
Project-URL: Git Clone URL, https://mudpy.org/code/mudpy/
Project-URL: License Texts, https://mudpy.org/license/
Project-URL: Release Files, https://mudpy.org/dist/mudpy/
Keywords: game,mud,telnet
Classifier: License :: OSI Approved :: ISC License (ISCL)
Classifier: Operating System :: POSIX
Classifier: Operating System :: Unix
Classifier: Programming Language :: Python
Classifier: Programming Language :: Python :: 3
Classifier: Programming Language :: Python :: 3.7
Classifier: Programming Language :: Python :: 3.8
Classifier: Programming Language :: Python :: 3.9
Classifier: Programming Language :: Python :: 3.10
Classifier: Programming Language :: Python :: 3.11
Classifier: Programming Language :: Python :: 3 :: Only
Classifier: Topic :: Communications
Classifier: Topic :: Communications :: BBS
Classifier: Topic :: Communications :: Chat
Classifier: Topic :: Games/Entertainment
Classifier: Topic :: Games/Entertainment :: Multi-User Dungeons (MUD)
Classifier: Topic :: Games/Entertainment :: Role-Playing
Classifier: Topic :: Internet
Requires-Python: >=3.7
License-File: LICENSE
License-File: AUTHORS
